<trace runtime="2000">
<start name="task1" time="0"/>
<start name="task2" time="15"/>
<start name="task3" time="35"/>
<start name="task1" time="100"/>
<start name="task2" time="195"/>
<start name="task1" time="200"/>
<continue name="task2" time="215"/>
<start name="task3" time="250"/>
<start name="task1" time="300"/>
<start name="task2" time="390"/>
<start name="task1" time="400"/>
<continue name="task2" time="415"/>
<start name="task1" time="500"/>
<start name="task3" time="515"/>
<start name="task2" time="585"/>
<start name="task1" time="600"/>
<continue name="task2" time="615"/>
<start name="task1" time="700"/>
<start name="task3" time="750"/>
<start name="task2" time="780"/>
<start name="task1" time="800"/>
<start name="task1" time="900"/>
<start name="task2" time="975"/>
<start name="task1" time="1000"/>
<start name="task3" time="1015"/>
<start name="task1" time="1100"/>
<start name="task2" time="1170"/>
<start name="task1" time="1200"/>
<start name="task3" time="1250"/>
<start name="task1" time="1300"/>
<start name="task2" time="1365"/>
<start name="task1" time="1400"/>
<start name="task1" time="1500"/>
<start name="task3" time="1515"/>
<start name="task2" time="1560"/>
<start name="task1" time="1600"/>
<start name="task1" time="1700"/>
<start name="task3" time="1750"/>
<start name="task2" time="1755"/>
<continue name="task3" time="1775"/>
<start name="task1" time="1800"/>
<start name="task1" time="1900"/>
<start name="task2" time="1950"/>
</trace>
